ndsampler/__init__.py
ndsampler/_internal.py
ndsampler/abstract_frames.py
ndsampler/abstract_sampler.py
ndsampler/category_tree.py
ndsampler/coco_dataset.py
ndsampler/coco_frames.py
ndsampler/coco_regions.py
ndsampler/coco_sampler.py
ndsampler/coerce_data.py
ndsampler/frame_cache.py
ndsampler/isect_indexer.py
ndsampler/toydata.py
ndsampler/utils/__init__.py
ndsampler/utils/util_futures.py
ndsampler/utils/util_gdal.py
ndsampler/utils/util_lru.py
ndsampler/utils/util_misc.py
ndsampler/utils/util_shape.py
ndsampler/utils/util_sklearn.py
ndsampler/utils/validate_cog.py
ndsampler-0.8.1.dist-info/licenses/LICENSE
ndsampler-0.8.1.dist-info/METADATA
ndsampler-0.8.1.dist-info/WHEEL
ndsampler-0.8.1.dist-info/top_level.txt
ndsampler-0.8.1.dist-info/RECORD
